{
    "request_number": 11,
    "timestamp": "2025-10-12 12:41:40",
    "model": "x-ai/grok-4-fast",
    "total_tokens": 7487,
    "total_logprob": -811.2994895095477,
    "avg_prob": 0.8973035295533992,
    "perplexity": 1.1144500908156623,
    "token_count": 7487,
    "function_count": 95,
    "class_count": 4,
    "num_lines": 845,
    "num_nonempty_lines": 732,
    "avg_line_len_all_chars": 35.30414201183432,
    "avg_line_len_nonempty_chars": 40.666666666666664,
    "avg_tokens_per_nonempty_line": 4.109289617486339,
    "ast_depth": 12,
    "import_count": 14,
    "import_names": [
        "csv",
        "dataclasses",
        "datetime",
        "enum",
        "flask",
        "json",
        "logging",
        "os",
        "pandas",
        "re",
        "sqlite3",
        "typing",
        "werkzeug",
        "zipfile"
    ],
    "import_redundancy_ratio": 0.0,
    "avg_function_size_lines": 7.063157894736842,
    "comment_density_percent": 8.19672131147541,
    "per_function_cyclomatic": {
        "init_db": 2,
        "process_12_19_2017_deletions": 1,
        "update_fabs_validation_rules": 1,
        "derive_gtas_window_data": 1,
        "manage_d_file_generation_cache": 2,
        "load_historical_fabs_data": 2,
        "derive_office_name": 1,
        "update_frec_derivations": 1,
        "validate_duns_record": 6,
        "validate_zip_ppop": 4,
        "handle_large_flexfields": 3,
        "derive_ppop_code_congressional_district": 3,
        "update_fabs_sample_file": 1,
        "prevent_double_publishing": 3,
        "generate_d_files_from_fabs_fpds": 2,
        "update_header_info_with_datetime": 1,
        "handle_wrong_file_extension": 2,
        "load_historical_fpds_data": 1,
        "show_submission_creator": 1,
        "get_file_f_format": 1,
        "provide_fabs_groups_frec": 1,
        "test_derivations_robust": 2,
        "ensure_zero_padded_fields": 1,
        "allow_individual_recipients_no_duns_error": 1,
        "show_publish_row_count": 1,
        "prevent_duplicate_transactions": 2,
        "submit_citywide_ppop_zip": 2,
        "update_error_codes_helpful": 1,
        "allow_zip_without_last4": 2,
        "ensure_historical_columns": 1,
        "access_additional_fpds_fields": 1,
        "add_submission_dashboard_info": 1,
        "download_uploaded_fabs_file": 1,
        "quick_access_broker_data": 1,
        "load_historical_fpds_best_way": 1,
        "appropriate_fabs_language": 1,
        "no_dabs_banners_in_fabs": 1,
        "fabs_readonly_dabs_access": 1,
        "reasonable_validation_time": 2,
        "correct_status_labels_dashboard": 1,
        "show_submission_periods": 1,
        "landing_page_nav_fabs_dabs": 1,
        "submit_with_quotes_preserve_zeros": 1,
        "redesigned_resources_page": 1,
        "report_user_testing_agencies": 1,
        "round2_dabs_fabs_edits": 1,
        "round2_homepage_edits": 1,
        "round3_help_edits": 1,
        "round2_help_edits": 1,
        "track_tech_thursday_issues": 1,
        "create_user_testing_summary": 1,
        "begin_user_testing": 1,
        "schedule_user_testing": 1,
        "design_ui_schedule": 1,
        "design_ui_audit": 1,
        "reset_environment_staging_max": 1,
        "flexfields_in_error_warning_files": 1,
        "update_fabs_deploy_production": 1,
        "clarify_cfda_error": 1,
        "ensure_sam_data_complete": 1,
        "index_domain_models": 1,
        "update_sql_codes_clarity": 1,
        "derive_funding_agency_code": 1,
        "max_length_legal_entity_address3": 1,
        "use_schema_v11_headers": 1,
        "map_federal_action_obligation_atom": 1,
        "link_sample_file_dialog": 1,
        "ensure_daily_fpds_update": 1,
        "access_raw_agency_published_files": 2,
        "fabs_submission_errors_accurate": 1,
        "frontend_urls_accurate": 1,
        "load_all_historical_fin_assist": 1,
        "get_file_level_errors": 1,
        "submission_dashboard_status": 1,
        "upload_and_validate_fabs": 11,
        "sync_d1_file_generation": 2,
        "check_fpds_update": 1,
        "access_published_fabs_files": 3,
        "ensure_only_grant_records_sent": 1,
        "receive_fabs_updates": 1,
        "ensure_deleted_fsrs_not_included": 1,
        "daily_financial_assist_update": 1,
        "deactivate_publish_button_derivations": 1,
        "prevent_nonexistent_correct_delete": 2,
        "update_broker_resources_validations_pp": 1,
        "no_nasa_grants_as_contracts": 3,
        "publish_fabs_submission": 4,
        "new_relic_useful_data": 1,
        "create_content_mockups": 1,
        "PublishStatus": 1,
        "SubmissionStatus": 1,
        "FABSRecord": 3,
        "__post_init__": 2,
        "ValidationResult": 4,
        "__init__": 3
    },
    "avg_cyclomatic_complexity": 1.5473684210526315,
    "max_cyclomatic_complexity": 11,
    "module_cyclomatic_complexity": 147,
    "syntax_valid": true,
    "flake8_error_count": 120,
    "flake8_error_breakdown": {
        "E": 95,
        "F": 8,
        "W": 17,
        "C": 0,
        "N": 0,
        "total": 120
    },
    "mypy_error_count": 3,
    "mypy_error_breakdown": {
        "return_type": 0,
        "argument_type": 2,
        "missing_return": 0,
        "attribute_error": 0,
        "annotation_issue": 0,
        "other": 1,
        "total": 3
    },
    "semantic_quality_score": 77.0,
    "execution_success": false,
    "execution_time_sec": 1.503,
    "exception_type": "APIError",
    "exception_message": "409 Client Error for http+docker://localnpipe/v1.51/containers/c973b6f3bd908462c790f18165922071fd340e8acc3234424c9b53d2cf8ad131/logs?stderr=1&stdout=1&timestamps=0&follow=0&tail=all: Conflict (\"can not get logs from container which is dead or marked for removal\")",
    "runtime_output": "",
    "total_credibility": 44.315
}